cryptodatapi/__init__.py
cryptodatapi/crypto_price.py
cryptodatapi/derivatives.py
cryptodatapi/dex.py
cryptodatapi/gainers.py
cryptodatapi/hist_price.py
cryptodatapi/lending.py
cryptodatapi/login.py
cryptodatapi/losers.py
cryptodatapi/news.py
cryptodatapi/spot.py
cryptodatapi/version.py
cryptodatapi-1.0.7.dist-info/LICENSE
cryptodatapi-1.0.7.dist-info/METADATA
cryptodatapi-1.0.7.dist-info/WHEEL
cryptodatapi-1.0.7.dist-info/top_level.txt
cryptodatapi-1.0.7.dist-info/RECORD
