Metadata-Version: 2.1
Name: cryptodatapi
Version: 1.0.7
Summary: Python SDK for integrating with Crypto API.
Home-page: https://horisystems.com/crypto-api/
Author: Hori Systems Limited
Author-email: support@horisystems.com
License: MIT
Project-URL: Bug Tracker, https://github.com/horisystems/cryptodatapi-py-sdk/issues
Project-URL: Changes, https://github.com/horisystems/cryptodatapi-py-sdk/blob/main/CHANGELOG.md
Project-URL: Documentation, https://docs.cryptodatapi.com/
Project-URL: Source Code, https://github.com/horisystems/cryptodatapi-py-sdk
Keywords: crypto,cryptocurrency,bitcoin,btc,ethereum,sol,bnb
Classifier: Development Status :: 5 - Production/Stable
Classifier: Intended Audience :: Developers
Classifier: License :: OSI Approved :: MIT License
Classifier: Operating System :: OS Independent
Classifier: Programming Language :: Python
Classifier: Programming Language :: Python :: 2
Classifier: Programming Language :: Python :: 2.7
Classifier: Programming Language :: Python :: 3
Classifier: Programming Language :: Python :: 3.4
Classifier: Programming Language :: Python :: 3.5
Classifier: Programming Language :: Python :: 3.6
Classifier: Programming Language :: Python :: 3.7
Classifier: Programming Language :: Python :: 3.8
Classifier: Programming Language :: Python :: 3.9
Classifier: Programming Language :: Python :: 3.10
Classifier: Programming Language :: Python :: 3.11
Classifier: Programming Language :: Python :: Implementation :: PyPy
Classifier: Topic :: Software Development :: Libraries :: Python Modules
Requires-Python: >=2.7, !=3.0.*, !=3.1.*, !=3.2.*, !=3.3.*
License-File: LICENSE
Requires-Dist: requests
